{
    "title": "World of Warcraft Vanilla Walkthroughs, Guides & More!",
    "description": "Quest database, item lookup, and NPC information for World of Warcraft Vanilla. Works perfectly in Safari Leopard WebKit / Aquafox on the G4.",
    "category": "gaming",
    "g4_friendly": 1,
    "featured": 0,
    "url": "https://classicdb.ch",
    "thumb": "https://classicdb.ch/images/logo2.png",
    "date": "2026-06-08",
    "author": "Technologyst Labs",
    "tags": [
        "wow",
        "world of warcraft",
        "wow vanilla",
        "vanilla",
        "classic",
        "classicdb",
        "classicdb.ch",
        "database",
        "quest database",
        "quests",
        "items",
        "item lookup",
        "npc",
        "walkthrough",
        "guide",
        "wiki",
        "web",
        "gaming",
        "mmo",
        "mmorpg",
        "rpg",
        "safari leopard webkit",
        "aquafox",
        "g4",
        "powermac",
        "powerpc",
        "ppc"
    ],
    "downloads": []
}
